sla_runner/__init__.py
sla_runner/__main__.py
sla_runner/sla_runner.py
sla_runner/version.py
sla_runner-0.0.18.dist-info/LICENSE
sla_runner-0.0.18.dist-info/METADATA
sla_runner-0.0.18.dist-info/WHEEL
sla_runner-0.0.18.dist-info/entry_points.txt
sla_runner-0.0.18.dist-info/top_level.txt
sla_runner-0.0.18.dist-info/RECORD
