Metadata-Version: 2.1
Name: sla-runner
Version: 0.0.18
Summary: A continuous test runner for gathering SLA data
Home-page: https://github.com/billtrust/sla-monitor-runner
Author: Jaime Wissner
Author-email: jwissner@billtrust.com
License: MIT
Keywords: sla-testing,aws-sla-reporting,sla-monitor,sla,continuous runner
Platform: UNKNOWN
Classifier: Intended Audience :: Developers
Classifier: Natural Language :: English
Classifier: License :: OSI Approved :: MIT License
Classifier: Programming Language :: Python
Classifier: Programming Language :: Python :: 3
Classifier: Programming Language :: Python :: 3.7
Requires-Dist: boto3 (<2.0,>=1.7.20)
Requires-Dist: botocore (<2.0,>=1.10.20)
